cppyythonizations/__init__.py
cppyythonizations/boost/__init__.py
cppyythonizations/boost/logic/__init__.py
cppyythonizations/boost/logic/tribool.py
cppyythonizations/boost/type_erasure/__init__.py
cppyythonizations/include/cereal/access.hpp
cppyythonizations/include/cereal/cereal.hpp
cppyythonizations/include/cereal/macros.hpp
cppyythonizations/include/cereal/specialize.hpp
cppyythonizations/include/cereal/version.hpp
cppyythonizations/include/cereal/archives/adapters.hpp
cppyythonizations/include/cereal/archives/binary.hpp
cppyythonizations/include/cereal/archives/json.hpp
cppyythonizations/include/cereal/archives/portable_binary.hpp
cppyythonizations/include/cereal/archives/xml.hpp
cppyythonizations/include/cereal/details/helpers.hpp
cppyythonizations/include/cereal/details/polymorphic_impl.hpp
cppyythonizations/include/cereal/details/polymorphic_impl_fwd.hpp
cppyythonizations/include/cereal/details/static_object.hpp
cppyythonizations/include/cereal/details/traits.hpp
cppyythonizations/include/cereal/details/util.hpp
cppyythonizations/include/cereal/external/base64.hpp
cppyythonizations/include/cereal/external/rapidjson/allocators.h
cppyythonizations/include/cereal/external/rapidjson/cursorstreamwrapper.h
cppyythonizations/include/cereal/external/rapidjson/document.h
cppyythonizations/include/cereal/external/rapidjson/encodedstream.h
cppyythonizations/include/cereal/external/rapidjson/encodings.h
cppyythonizations/include/cereal/external/rapidjson/filereadstream.h
cppyythonizations/include/cereal/external/rapidjson/filewritestream.h
cppyythonizations/include/cereal/external/rapidjson/fwd.h
cppyythonizations/include/cereal/external/rapidjson/istreamwrapper.h
cppyythonizations/include/cereal/external/rapidjson/memorybuffer.h
cppyythonizations/include/cereal/external/rapidjson/memorystream.h
cppyythonizations/include/cereal/external/rapidjson/ostreamwrapper.h
cppyythonizations/include/cereal/external/rapidjson/pointer.h
cppyythonizations-1.2.5.dist-info/AUTHORS
cppyythonizations-1.2.5.dist-info/COPYING
cppyythonizations-1.2.5.dist-info/METADATA
cppyythonizations-1.2.5.dist-info/WHEEL
cppyythonizations-1.2.5.dist-info/top_level.txt
cppyythonizations-1.2.5.dist-info/RECORD
