Metadata-Version: 2.1
Name: cppyythonizations
Version: 1.2.5
Summary: A collection of Pythonizations for cppyy
Author-email: Julian Rüth <julian.rueth@fsfe.org>
Project-URL: Homepage, https://github.com/flatsurf/cppyythonizations
Project-URL: Repository, https://github.com/flatsurf/cppyythonizations.git
Project-URL: Issues, https://github.com/flatsurf/cppyythonizations/issues
Project-URL: Changelog, https://github.com/flatsurf/cppyythonizations/blob/master/ChangeLog
Classifier: License :: OSI Approved :: MIT License
License-File: COPYING
License-File: AUTHORS
Requires-Dist: cppyy
